pymitv/__init__.py
pymitv/control.py
pymitv/discover.py
pymitv/navigator.py
pymitv/tv.py
pymitv-1.5.0.dist-info/LICENSE.txt
pymitv-1.5.0.dist-info/METADATA
pymitv-1.5.0.dist-info/WHEEL
pymitv-1.5.0.dist-info/top_level.txt
pymitv-1.5.0.dist-info/RECORD
