Metadata-Version: 2.1
Name: pymitv
Version: 1.5.0
Summary: A Python 3 based Xiaomi TV remote
Home-page: https://github.com/simse/pymitv
Author: Simon Sorensen
Author-email: teamangryghast@gmail.com
License: UNKNOWN
Keywords: xiaomi remote tv
Platform: UNKNOWN
Classifier: Development Status :: 4 - Beta
Classifier: Intended Audience :: Developers
Classifier: License :: OSI Approved :: MIT License
Classifier: Programming Language :: Python :: 3.6
Classifier: Programming Language :: Python :: 3.7
Requires-Dist: requests
